xtensor/__init__.py
xtensor/alignment.py
xtensor/coordinates.py
xtensor/dataset.py
xtensor/datatensor.py
xtensor/indexes.py
xtensor/variable.py
xtensor_datatensor-0.1.0.dist-info/licenses/LICENSE
xtensor_datatensor-0.1.0.dist-info/METADATA
xtensor_datatensor-0.1.0.dist-info/WHEEL
xtensor_datatensor-0.1.0.dist-info/top_level.txt
xtensor_datatensor-0.1.0.dist-info/RECORD
