Metadata-Version: 2.4
Name: xtensor-datatensor
Version: 0.1.0
Summary: Lightweight DataTensor wrapper that mimics a subset of xarray.DataArray APIs on top of torch.Tensor.
Author: Codex Assistant
License-Expression: MIT
Keywords: tensor,data,xarray,pytorch
Requires-Python: >=3.9
License-File: LICENSE
Requires-Dist: numpy>=1.23
Requires-Dist: pandas>=1.5
Requires-Dist: torch>=1.13
Requires-Dist: xarray>=2023.1
Provides-Extra: dev
Requires-Dist: pytest>=7.0; extra == "dev"
Dynamic: license-file
